setup.py
damhur_distributions/Binomialdistribution.py
damhur_distributions/Gaussiandistribution.py
damhur_distributions/Generaldistribution.py
damhur_distributions/__init__.py
damhur_distributions.egg-info/PKG-INFO
damhur_distributions.egg-info/SOURCES.txt
damhur_distributions.egg-info/dependency_links.txt
damhur_distributions.egg-info/not-zip-safe
damhur_distributions.egg-info/top_level.txt