Metadata-Version: 1.0
Name: damhur-distributions
Version: 0.2
Summary: Gaussian and Binomial distributions
Home-page: UNKNOWN
Author: Mario Damhur
Author-email: damhur92@gmail.com
License: UNKNOWN
Platform: UNKNOWN
